tf_metric_learning-1.0.12-py3.10-nspkg.pth
examples/__init__.py
examples/base.py
examples/classification.py
examples/contrastive.py
examples/npair.py
examples/proxy_anchor.py
examples/soft_triple.py
examples/triplet.py
tf_metric_learning/layers/__init__.py
tf_metric_learning/layers/classification.py
tf_metric_learning/layers/contrastive.py
tf_metric_learning/layers/multisimilarity.py
tf_metric_learning/layers/npair.py
tf_metric_learning/layers/proxy_anchor.py
tf_metric_learning/layers/soft_triple.py
tf_metric_learning/layers/triplet.py
tf_metric_learning/layers/utils.py
tf_metric_learning/miners/__init__.py
tf_metric_learning/miners/annoy.py
tf_metric_learning/utils/__init__.py
tf_metric_learning/utils/constants.py
tf_metric_learning/utils/index.py
tf_metric_learning/utils/projector.py
tf_metric_learning/utils/recall.py
tf_metric_learning-1.0.12.dist-info/LICENSE
tf_metric_learning-1.0.12.dist-info/METADATA
tf_metric_learning-1.0.12.dist-info/WHEEL
tf_metric_learning-1.0.12.dist-info/namespace_packages.txt
tf_metric_learning-1.0.12.dist-info/top_level.txt
tf_metric_learning-1.0.12.dist-info/RECORD
