Metadata-Version: 2.1
Name: tf-metric-learning
Version: 1.0.12
Summary: Image similarity, metric learning loss functions for TensorFlow 2+.
Home-page: https://github.com/Ximilar-com/tf-metric-learning
Author: Michal Lukac & Ximilar.com Team
Author-email: tech@ximilar.com
License: MIT
Keywords: machine learning,multimedia,image
Platform: UNKNOWN
Classifier: Development Status :: 3 - Alpha
Classifier: License :: OSI Approved :: MIT License
Classifier: Programming Language :: Python :: 3.6
Classifier: Topic :: Scientific/Engineering :: Artificial Intelligence
License-File: LICENSE
